LICENSE
README.rst
setup.py
src/usda/__init__.py
src/usda/_min_dependencies.py
src/usda.egg-info/PKG-INFO
src/usda.egg-info/SOURCES.txt
src/usda.egg-info/dependency_links.txt
src/usda.egg-info/not-zip-safe
src/usda.egg-info/requires.txt
src/usda.egg-info/top_level.txt
src/usda/data_process/__init__.py
src/usda/data_process/_geoinfodata_conversion.py
src/usda/data_process/_image_pixel_sampling_zoom.py
src/usda/data_process/_kitti_dataprocess.py
src/usda/data_process/_landsat_dataprocess.py
src/usda/data_process/_naip_dataprocess.py
src/usda/data_process/_osm_dataprocess.py
src/usda/data_process/_raster_dataprocess.py
src/usda/data_process/_tiler_calculation.py
src/usda/data_visual/__init__.py
src/usda/data_visual/_colors.py
src/usda/data_visual/_plot_style.py
src/usda/data_visual/_worldcover_plot_style.py
src/usda/data_visualization/__init__.py
src/usda/data_visualization/_chart_custom.py
src/usda/data_visualization/_colors.py
src/usda/data_visualization/_dynamic_streetView_visual_perception.py
src/usda/data_visualization/_gdf_plot.py
src/usda/data_visualization/_gif_show.py
src/usda/data_visualization/_graphic_drawing.py
src/usda/data_visualization/_image_process.py
src/usda/data_visualization/_img_feature_extraction.py
src/usda/data_visualization/_img_theme_color.py
src/usda/data_visualization/_imgs_layout_show.py
src/usda/data_visualization/_imgs_show.py
src/usda/data_visualization/_knee_line_graph.py
src/usda/data_visualization/_moving_average_inflection.py
src/usda/data_visualization/_panorama_show.py
src/usda/data_visualization/_plot_single_function.py
src/usda/data_visualization/_raster_percentile_slider.py
src/usda/data_visualization/_raster_show.py
src/usda/data_visualization/_stats_charts.py
src/usda/data_visualization/_superpixel_segmentation_show.py
src/usda/data_visualization/_table_show.py
src/usda/data_visualization/_tile_show.py
src/usda/data_visualization/data_generator.py
src/usda/data_visualization/knee_locator.py
src/usda/database/__init__.py
src/usda/database/_data_file_rw.py
src/usda/database/_data_format_conversion.py
src/usda/database/_database.py
src/usda/database/_read_matlab_fig.py
src/usda/datasets/__init__.py
